{
  "project_info": {
    "project_number": "159628540720",
    "project_id": "scanupp-807fd",
    "storage_bucket": "scanupp-807fd.firebasestorage.app"
  },
  "client": [
    {
      "client_info": {
        "mobilesdk_app_id": "1:159628540720:android:e3d1d39e5e37d1eb43e6f5",
        "android_client_info": {
          "package_name": "com.visiongo.scanupp"
        }
      },
      "oauth_client": [
        {
          "client_id": "159628540720-81pt5h52361c9qm9l8rb4omfmaaao6b9.apps.googleusercontent.com",
          "client_type": 1,
          "android_info": {
            "package_name": "com.visiongo.scanupp",
            "certificate_hash": "374b08d0c95bd02333f4701b8497ad8f54491756"
          }
        },
        {
          "client_id": "159628540720-o2ckqdtkdei1ohmff4q85n7huovu0v95.apps.googleusercontent.com",
          "client_type": 1,
          "android_info": {
            "package_name": "com.visiongo.scanupp",
            "certificate_hash": "afe22603516f39dbab8d8e03ed4a9a2cd22ffc51"
          }
        },
        {
          "client_id": "159628540720-tn2bcg6a2hgfgn29g1vm48khlaqvctke.apps.googleusercontent.com",
          "client_type": 3
        }
      ],
      "api_key": [
        {
          "current_key": "AIzaSyB8XC_VcbFzb0cKNXIRcfx094kR66JYGJE"
        }
      ],
      "services": {
        "appinvite_service": {
          "other_platform_oauth_client": [
            {
              "client_id": "159628540720-tn2bcg6a2hgfgn29g1vm48khlaqvctke.apps.googleusercontent.com",
              "client_type": 3
            }
          ]
        }
      }
    }
  ],
  "configuration_version": "1"
}